Workbook

Sheet Simulador
B2: SIMULADOR DE INVESTIMENTOS EM FIIs
B4: CONFIGURAÇÕES
B5: Salário mensal | D5: 5000
B6: Rendimento da carteira ao mês | D6: 0.006
B7: Sugestão de investimento (30%) | D7: =D5*30% -> 1500
B9: INVESTIMENTO MENSAL
B10: Quanto investir por mês? | D10: 550
B11: Por quantos anos? | D11: 5
B12: Taxa de rendimento mensal? | D12: 0.006
B13: Patrimônio acumulado | D13: =FV(D12,D11*12,-D10,0,0) -> 39580.604
B14: Dividendos mensais estimados | D14: =D13*D6 -> 237.48363
B17: CENÁRIOS DE INVESTIMENTO
B18: Prazo | C18: Patrimônio acumulado | D18: Dividendos/mês
B19: 2 | C19: =FV($D$12,B19*12,-$D$10,0,0) -> 14152.168 | D19: =C19*$D$6 -> 84.913011
B20: 5 | C20: =FV($D$12,B20*12,-$D$10,0,0) -> 39580.604 | D20: =C20*$D$6 -> 237.48363
B21: 10 | C21: =FV($D$12,B21*12,-$D$10,0,0) -> 96251.655 | D21: =C21*$D$6 -> 577.50993
B22: 20 | C22: =FV($D$12,B22*12,-$D$10,0,0) -> 293569.29 | D22: =C22*$D$6 -> 1761.4157
B23: 30 | C23: =FV($D$12,B23*12,-$D$10,0,0) -> 698073.99 | D23: =C23*$D$6 -> 4188.444
B26: DISTRIBUIÇÃO POR PERFIL
B27: Perfil do investidor | C27: Agressivo
B28: Valor investido por mês | D28: =D10 -> 550
B30: Tipo de FII | C30: Percentual | D30: Valor mensal
B31: Papel | C31: =VLOOKUP($C$27&"|"&B31,'Bases Perfis'!$A$2:$D$19,4,FALSE) -> 0.2 | D31: =C31*$D$28 -> 110
B32: Tijolo | C32: =VLOOKUP($C$27&"|"&B32,'Bases Perfis'!$A$2:$D$19,4,FALSE) -> 0.25 | D32: =C32*$D$28 -> 137.5
B33: Híbridos | C33: =VLOOKUP($C$27&"|"&B33,'Bases Perfis'!$A$2:$D$19,4,FALSE) -> 0.15 | D33: =C33*$D$28 -> 82.5
B34: FOFs | C34: =VLOOKUP($C$27&"|"&B34,'Bases Perfis'!$A$2:$D$19,4,FALSE) -> 0.1 | D34: =C34*$D$28 -> 55
B35: Desenvolvimento | C35: =VLOOKUP($C$27&"|"&B35,'Bases Perfis'!$A$2:$D$19,4,FALSE) -> 0.2 | D35: =C35*$D$28 -> 110
B36: Hotelarias | C36: =VLOOKUP($C$27&"|"&B36,'Bases Perfis'!$A$2:$D$19,4,FALSE) -> 0.1 | D36: =C36*$D$28 -> 55
D37: =SUM(D31:D36) -> 550

Sheet Bases Perfis
A1: Chave | B1: Perfil | C1: Tipo de FII | D1: Percentual
A2: Conservador|Papel | B2: Conservador | C2: Papel | D2: 0.4
A3: Conservador|Tijolo | B3: Conservador | C3: Tijolo | D3: 0.35
A4: Conservador|Híbridos | B4: Conservador | C4: Híbridos | D4: 0.1
A5: Conservador|FOFs | B5: Conservador | C5: FOFs | D5: 0.1
A6: Conservador|Desenvolvimento | B6: Conservador | C6: Desenvolvimento | D6: 0.03
A7: Conservador|Hotelarias | B7: Conservador | C7: Hotelarias | D7: 0.02
A8: Moderado|Papel | B8: Moderado | C8: Papel | D8: 0.32
A9: Moderado|Tijolo | B9: Moderado | C9: Tijolo | D9: 0.35
A10: Moderado|Híbridos | B10: Moderado | C10: Híbridos | D10: 0.08
A11: Moderado|FOFs | B11: Moderado | C11: FOFs | D11: 0.05
A12: Moderado|Desenvolvimento | B12: Moderado | C12: Desenvolvimento | D12: 0.1
A13: Moderado|Hotelarias | B13: Moderado | C13: Hotelarias | D13: 0.1
... A19: Agressivo|Hotelarias | B19: Agressivo | C19: Hotelarias | D19: 0.1
